dohyeon/__init__.py
dohyeon-1.0.0.3.dist-info/METADATA
dohyeon-1.0.0.3.dist-info/WHEEL
dohyeon-1.0.0.3.dist-info/top_level.txt
dohyeon-1.0.0.3.dist-info/RECORD
