Metadata-Version: 2.1
Name: dohyeon
Version: 1.0.0.3
Summary: dohyeon
Home-page: 
Author: dohyeon
Author-email: ehgus9363@gmail.com
Requires-Python: >=3
